{
  "description": "Configuration file for IGME IELIG site codes to scrape",
  "base_url": "https://info.igme.es/ielig/LIGInfo.aspx?codigo=",
  "excluded_codes": [
    "IB200a",
    "IB200w",
    "IB200x",
    "IB200y",
    "IB200z",
    "IB034a",
    "IB034k",
    "IB034l",
    "IB034m",
    "IB034n",
    "IB034o",
    "IB034p",
    "IB034q",
    "IB034r",
    "IB034s",
    "IB034t",
    "IB034u",
    "IB034v",
    "IB034w",
    "IB034x",
    "IB034y",
    "IB034z"
  ],
  "site_series": [
    {
      "base_code": "IB200",
      "include_base": true,
      "suffixes": "a-z",
      "description": "IB200 series sites"
    },
    {
      "base_code": "IB034",
      "include_base": true,
      "suffixes": "a-z",
      "description": "IB034 series sites"
    }
  ],
  "individual_sites": [
    {
      "code": "IBs189",
      "description": "Additional site"
    },
    {
      "code": "IB207",
      "description": "Galve/Teruel site"
    },
    {
      "code": "IB208",
      "description": "Galve/Teruel site"
    }
  ],
  "custom_sites": [
    {
      "code": "T0001",
      "name": "Custom Test Site 1",
      "latitude": 40.4168,
      "longitude": -3.7038,
      "description": "Example custom site - Madrid"
    },
    {
      "code": "T0002",
      "name": "Custom Test Site 2",
      "latitude": 41.3851,
      "longitude": 2.1734,
      "description": "Example custom site - Barcelona"
    }
  ],
  "default_values": {
    "valor_turistico": "5.0",
    "confidencialidad": "Public",
    "route_difficulty": "Medium"
  }
}
